cdk_express_pipeline/__init__.py
cdk_express_pipeline/py.typed
cdk_express_pipeline/_jsii/__init__.py
cdk_express_pipeline/_jsii/cdk-express-pipeline@2.2.0.jsii.tgz
cdk_express_pipeline-2.2.0.dist-info/LICENSE
cdk_express_pipeline-2.2.0.dist-info/METADATA
cdk_express_pipeline-2.2.0.dist-info/WHEEL
cdk_express_pipeline-2.2.0.dist-info/top_level.txt
cdk_express_pipeline-2.2.0.dist-info/RECORD
